fastprocesses/__init__.py
fastprocesses/api/__init__.py
fastprocesses/api/manager.py
fastprocesses/api/router.py
fastprocesses/api/server.py
fastprocesses/common.py
fastprocesses/core/__init__.py
fastprocesses/core/base_process.py
fastprocesses/core/cache.py
fastprocesses/core/config.py
fastprocesses/core/exceptions.py
fastprocesses/core/logging.py
fastprocesses/core/models.py
fastprocesses/core/redis_connection.py
fastprocesses/core/types.py
fastprocesses/processes/__init__.py
fastprocesses/processes/process_registry.py
fastprocesses/py.typed
fastprocesses/static/style.css
fastprocesses/templates/landing.html
fastprocesses/worker/__init__.py
fastprocesses/worker/celery_app.py
fastprocesses-0.15.5.dist-info/AUTHORS.md
fastprocesses-0.15.5.dist-info/METADATA
fastprocesses-0.15.5.dist-info/WHEEL
fastprocesses-0.15.5.dist-info/entry_points.txt
fastprocesses-0.15.5.dist-info/RECORD
