Metadata-Version: 2.3
Name: fastprocesses
Version: 0.15.5
Summary: A library to create a FastAPI-based  OGC API Processes wrapper around existing projects.
Author: Stefan Schuhart
Author-email: stefan.schuhart@gv.hamburg.de
Requires-Python: >=3.10
Classifier: Development Status :: 3 - Alpha
Classifier: Intended Audience :: Developers
Classifier: Programming Language :: Python
Classifier: Programming Language :: Python :: 3
Classifier: Programming Language :: Python :: 3 :: Only
Classifier: Programming Language :: Python :: 3.10
Classifier: Programming Language :: Python :: 3.11
Classifier: Programming Language :: Python :: 3.12
Classifier: Topic :: Software Development
Classifier: Topic :: Utilities
Classifier: Typing :: Typed
Requires-Dist: celery (>=5.4.0,<6.0.0)
Requires-Dist: fastapi (>=0.115.8,<0.116.0)
Requires-Dist: jinja2 (>=3.1.6,<4.0.0)
Requires-Dist: jsonschema (>=4.23.0,<5.0.0)
Requires-Dist: loguru (>=0.7.3,<0.8.0)
Requires-Dist: pydantic (>=2.10.6,<3.0.0)
Requires-Dist: pydantic-settings (>=2.7.1,<3.0.0)
Requires-Dist: pyyaml (>=6.0.2,<7.0.0)
Requires-Dist: redis (>=6.1.0,<7.0.0)
Requires-Dist: uvicorn (>=0.34.0,<0.35.0)
Project-URL: Changelog, https://github.com/StefanSchuhart/fastProcesses/CHANGELOG.md
Project-URL: Documentation, https://github.com/StefanSchuhart/fastProcesses/README.md
Project-URL: Homepage, https://github.com/StefanSchuhart/fastProcesses
Project-URL: Repository, https://github.com/StefanSchuhart/fastProcesses
